Workbook
Name Access_Control: '[1]Item Budgets'!$B$156:$B$167
Name Audio_Visual: '[1]Item Budgets'!$B$167:$B$178
Name Beam: #REF!
Name Beams: #REF!
Name BeamTon: #REF!
Name Channel: #REF!
Name Channels: #REF!
Name ChannelTon: #REF!
Name CHSs: #REF!
Name Column: #REF!
Name Columns: #REF!
Name ColumnTon: #REF!
Name CONTAINMENT: '[1]Item Budgets'!$B$95:$B$111
Name DISTRIBUTION: '[1]Item Budgets'!$B$123:$B$134
Name EMERGENCY_LIGHTING: '[1]Item Budgets'!$B$23:$B$34
Name Equal: #REF!
Name EqualTon: #REF!
Name FIRE_ALARM: '[1]Item Budgets'!$B$112:$B$123
Name Heating_Interface: '[1]Item Budgets'!$B$178:$B$189
Name Lighting: '[1]Item Budgets'!$B$4:$B$23
Name LIGHTING_CONTROL: '[1]Item Budgets'!$B$34:$B$45
Name LIST: [1]Containment!#REF!
Name List1: #REF!
Name List2: #REF!
Name List3: #REF!
Name Mechanical_Supplies: '[1]Item Budgets'!$B$134:$B$145
Name MISCELLANEOUS: '[1]Item Budgets'!$B$189:$B$207
Name PCFTon: #REF!
Name PFC: #REF!
Name PFCs: #REF!
Name PFCTon: #REF!
Name PRELIMS: '[1]Item Budgets'!$B$207:$B$216
Name RHS: #REF!
Name RHSs: #REF!
Name RHSTon: #REF!
Name RSJ: #REF!
Name RSJs: #REF!
Name RSJTon: #REF!
Name SHS: #REF!
Name SHSs: #REF!
Name SHSsTon: #REF!
Name SHSTon: #REF!
Name Site_Temporaries: '[1]Item Budgets'!$B$217:$B$228
Name SMALL_POWER: '[1]Item Budgets'!$B$45:$B$95
Name Steels: #REF!
Name Type: #REF!,#REF!,#REF!,#REF!,#REF!,#REF!,#REF!,#REF!,#REF!
Name Types: '[2]Type List'!$A$2:$A$8
Name Unequal: #REF!
Name UnequalTon: #REF!
Name Ventilation: '[1]Item Budgets'!$B$145:$B$156

Sheet Cover Letter
A12: Client | B12: ='Quotation '!C3 -> Pride Developments
A13: Project Reference | B13: ='Quotation '!C4 -> Library and Brandon Youth
A14: Site Address | B14: ='Quotation '!C5 -> Library and Brandon youth centre, 19 Maddock Way Cooks Road, SE17 3NH
A15: Date | B15: ='Quotation '!C6 -> 46085
A16: Contact | B16: estimating@fensterglazing.com / adam@fensterglazing.com
A19: Quotation Summary: Aluminium/uPVC/Composite Units
B21: Sub – Total: | C21: ='Quotation '!H19 -> 20400
B22: (Inclusive of supply and installation)
B23: VAT (20%): | C23: =SUM(C21*0.2) -> 4080
B24: Total Quotation Value: | C24: =SUM(C21+C23) -> 24480
A27: Notes & Clarifications
A28: 1. This price excludes EPDM, internal finishes, skips, and scaffolding, which are assumed to be provided by others. Should you require cost information for any of these elements, we would be happy to provide it.
A29: Design changes
A30: 1.
A31: 2.

Sheet Quotation 
B2: Fenster Glazing 98 Alston Drive Milton Keynes, Bucks MK12 9HF 01908 429 200 - www.fensterglazing.com
B3: Client: | C3: Pride Developments | J3: Supplier used: | K3: BDC
B4: Project Reference: | C4: Library and Brandon Youth
B5: Site Address: Library and Brandon youth centre, 19 Maddock Way Cooks Road, SE17 3NH | C5: Library and Brandon youth centre, 19 Maddock Way Cooks Road, SE17 3NH
B6: Date: | C6: 46085
C8: Description | D8: Size | E8: Qty | F8: Unit | G8: Unit Rate | H8: Total
C9: Aluminium Units | I9: Frames | J9: Glass | K9: Additional | L9: CW | M9: CW LABOUR | N9: CW SQM
B10: SAW | C10: W1 | D10: 10000 x 10000 | E10: 1 | F10: nr | G10: =I10+J10+K10+IF(B10="UPD",950,IF(B10="SAD",1150,IF(B10="DAD",1950,IF(B10="ELAW",1000,IF(B10="LAW",600,IF(B10="MAW",500,IF(B10="SAW",400,IF(B10="LPVC",400,IF(B10="MPVC",350,IF(B10="SPVC",300,IF(B10="SADLAW",1950,IF(B10="SADMAW",1850,IF(B10="SADSAW",1650,0))))))))))))) -> 500 | H10: =IF(AND(E10<>"", G10<>""), E10*G10, "") -> 500 | I10: 100 | L10: =SUM(N10*850) -> 85000 | M10: =SUM(N10*150) -> 15000 | N10: =(TRIM(LEFT(D10,FIND("x",D10)-1)) * TRIM(MID(D10,FIND("x",D10)+1,LEN(D10)))) / 1000000 -> 100 | O10: {=SUM(E10*I10:J10)} -> 100
B11: MAW | C11: W1 | D11: 2000 x 2000 | E11: 1 | F11: nr | G11: =I11+J11+K11+IF(B11="UPD",950,IF(B11="SAD",1150,IF(B11="DAD",1950,IF(B11="ELAW",1000,IF(B11="LAW",600,IF(B11="MAW",500,IF(B11="SAW",400,IF(B11="LPVC",400,IF(B11="MPVC",350,IF(B11="SPVC",300,IF(B11="SADLAW",1950,IF(B11="SADMAW",1850,IF(B11="SADSAW",1650,0))))))))))))) -> 700 | H11: =IF(AND(E11<>"", G11<>""), E11*G11, "") -> 700 | I11: 200 | L11: =SUM(N11*850) -> 3400 | M11: =SUM(N11*150) -> 600 | N11: =(TRIM(LEFT(D11,FIND("x",D11)-1)) * TRIM(MID(D11,FIND("x",D11)+1,LEN(D11)))) / 1000000 -> 4
B12: DAD | C12: W2 | D12: 3000 x 3000 | E12: 1 | F12: nr | G12: =I12+J12+K12+IF(B12="UPD",950,IF(B12="SAD",1150,IF(B12="DAD",1950,IF(B12="ELAW",1000,IF(B12="LAW",600,IF(B12="MAW",500,IF(B12="SAW",400,IF(B12="LPVC",400,IF(B12="MPVC",350,IF(B12="SPVC",300,IF(B12="SADLAW",1950,IF(B12="SADMAW",1850,IF(B12="SADSAW",1650,0))))))))))))) -> 2250 | H12: =IF(AND(E12<>"", G12<>""), E12*G12, "") -> 2250 | I12: 300 | L12: =SUM(N12*850) -> 7650 | M12: =SUM(N12*150) -> 1350 | N12: =(TRIM(LEFT(D12,FIND("x",D12)-1)) * TRIM(MID(D12,FIND("x",D12)+1,LEN(D12)))) / 1000000 -> 9
C13: E2 | D13: 4000 x 4000 | F13: nr | G13: =I13+J13+K13+IF(B13="UPD",950,IF(B13="SAD",1150,IF(B13="DAD",1950,IF(B13="ELAW",1000,IF(B13="LAW",600,IF(B13="MAW",500,IF(B13="SAW",400,IF(B13="LPVC",400,IF(B13="MPVC",350,IF(B13="SPVC",300,IF(B13="SADLAW",1950,IF(B13="SADMAW",1850,IF(B13="SADSAW",1650,0))))))))))))) -> 0 | H13: =IF(AND(E13<>"", G13<>""), E13*G13, "") | L13: =SUM(N13*850) -> 13600 | M13: =SUM(N13*150) -> 2400 | N13: =(TRIM(LEFT(D13,FIND("x",D13)-1)) * TRIM(MID(D13,FIND("x",D13)+1,LEN(D13)))) / 1000000 -> 16
C14: E4 | D14: 4000 x 4500 | F14: nr | G14: =I14+J14+K14+IF(B14="UPD",950,IF(B14="SAD",1150,IF(B14="DAD",1950,IF(B14="ELAW",1000,IF(B14="LAW",600,IF(B14="MAW",500,IF(B14="SAW",400,IF(B14="LPVC",400,IF(B14="MPVC",350,IF(B14="SPVC",300,IF(B14="SADLAW",1950,IF(B14="SADMAW",1850,IF(B14="SADSAW",1650,0))))))))))))) -> 0 | H14: =IF(AND(E14<>"", G14<>""), E14*G14, "") | L14: =SUM(N14*850) -> 15300 | M14: =SUM(N14*150) -> 2700 | N14: =(TRIM(LEFT(D14,FIND("x",D14)-1)) * TRIM(MID(D14,FIND("x",D14)+1,LEN(D14)))) / 1000000 -> 18
G15: =I15+J15+K15+IF(B15="UPD",950,IF(B15="SAD",1150,IF(B15="DAD",1950,IF(B15="ELAW",1000,IF(B15="LAW",600,IF(B15="MAW",500,IF(B15="SAW",400,IF(B15="LPVC",400,IF(B15="MPVC",350,IF(B15="SPVC",300,IF(B15="SADLAW",1950,IF(B15="SADMAW",1850,IF(B15="SADSAW",1650,0))))))))))))) -> 0 | H15: =IF(AND(E15<>"", G15<>""), E15*G15, "")
C17: INSTALLATION | H17: {=SUMPRODUCT(E10:E317*IF(M10:M317="",140,M10:M317))} -> 16950
C19: TOTAL* | H19: =SUM(H10:H17) -> 20400
C23: OPTIONAL
C24: EPDM | H24: {=SUMPRODUCT( IFERROR( ((VALUE(TRIM(LEFT($D$10:$D$17,FIND("x",$D$10:$D$17)-1)))/1000) * (VALUE(TRIM(MID($D$10:$D$17,FIND("x",$D$10:$D$17)+1,LEN($D$10:$D$17))))/1000) * 25) * $E$10:$E$17, 0 ) )} -> 2825
C25: MASTIC | H25: {=SUMPRODUCT( IFERROR( ( ( (VALUE(TRIM(LEFT($D$10:$D$904,FIND("x",$D$10:$D$904)-1))))+ (VALUE(TRIM(MID($D$10:$D$904,FIND("x",$D$10:$D$904)+1,LEN($D$10:$D$904))))) )*2/1000*5 )*$E$10:$E$904, 0 ) )} -> 300
C29: notes
C30: EPDM | H30: {=SUMPRODUCT( IFERROR( ((VALUE(TRIM(LEFT($D$10:$D$17,FIND("x",$D$10:$D$17)-1)))/1000) * (VALUE(TRIM(MID($D$10:$D$17,FIND("x",$D$10:$D$17)+1,LEN($D$10:$D$17))))/1000) * 25) * $E$10:$E$17, 0 ) )} -> 2825
C31: MASTIC | H31: {=SUMPRODUCT( IFERROR( ( ( (VALUE(TRIM(LEFT($D$10:$D$904,FIND("x",$D$10:$D$904)-1))))+ (VALUE(TRIM(MID($D$10:$D$904,FIND("x",$D$10:$D$904)+1,LEN($D$10:$D$904))))) )*2/1000*5 )*$E$10:$E$904, 0 ) )} -> 300
B34: * Total value excluding VAT.
B35: ** This pricing document should be read in conjunction with the accompanying cover letter and Standard Terms and Conditions.

Sheet Drawings 

Sheet Terms & Condition
A6: TERMS AND CONDITIONS
A7: 1. Consumer Notice Where the client is acting as a consumer, nothing in these Terms and Conditions shall affect the client’s statutory rights under the Consumer Rights Act 2015 or related consumer protection legislation.
A8: 2. Quotation Validity All quotations provided by Fenster Glazing & Locks Ltd are valid for 30 days from the date of issue, unless agreed otherwise. All quotations are subject to final site survey and measurement verification.
A9: 3. Deposit and Payment Terms Fenster Glazing & Locks Ltd requires receipt of a Purchase Order or a deposit of 50% of the total quotation value prior to commencement of works, in order to secure scheduling and procurement of materials. The remaining 50% balance is due upon completion of installation and client sign-off.
A10: 4. Late Payment All invoices are payable in accordance with the terms above. Any sums not paid within 30 calendar days of the invoice date will be considered overdue and will attract interest at the statutory rate of 4% per annum above the Bank of England base rate, applicable at the time.
A11: 5. Guarantee and Warranty Fenster Glazing & Locks Ltd provides a 10-year warranty covering all glass and frame products supplied and installed by the company. This warranty covers defects in materials (as supplied) and workmanship (installation). Furthermore, this warranty is subject to the terms and conditions of any applicable manufacturer warranties. It does not cover damage resulting from misuse, accidental or intentional damage, vandalism, inadequate or incorrect maintenance, or external factors, including severe weather conditions.
A12: 6. Order Confirmation & Site Survey Upon receipt of a valid Purchase Order, the quotation shall be converted into an order confirmation. A site survey shall then be undertaken to verify final measurements and site conditions. Where required, the order confirmation shall be updated and reissued to reflect verified measurements or agreed amendments. A sign-off sheet will be issued for client approval prior to manufacture or procurement of materials. Any changes to specifications, measurements, or costs identified as a result of the site survey or client-requested amendments shall be confirmed in writing and agreed prior to proceeding.
A13: 7. Manufacture, Delivery, and Installation Manufacture and procurement of materials shall commence only following receipt of the signed sign-off sheet. Once manufacture has commenced, changes or cancellations may not be possible and, where accommodated, may be subject to additional costs and revised lead times. Upon completion of manufacture, goods shall be delivered either to Fenster Glazing & Locks Ltd’s warehouse or directly to site, as agreed. Installation shall be carried out by Fenster Glazing & Locks Ltd in accordance with the agreed order confirmation and programme. Installation dates are indicative and subject to site readiness, access, and the client fulfilling its obligations.
A14: 8. Supplier Delays and Liability Fenster Glazing & Locks Ltd shall not be liable for delays, additional costs, losses, or consequential damages arising from delays, defects, or errors caused by third-party suppliers or manufacturers. Fenster Glazing & Locks Ltd will use reasonable endeavours to mitigate the impact of such delays and shall keep the client informed of any material changes to programme or availability. Where reasonably possible, alternative solutions may be proposed for the client’s consideration.
A15: 9. Site Access and Conditions The client shall be responsible for ensuring that safe, clear, and uninterrupted access to the installation site is available during agreed working hours and that site conditions are suitable for the works to proceed. Fenster Glazing & Locks Ltd reserves the right to suspend works where suitable access or site conditions are not provided. Any additional costs incurred as a result of restricted access, inadequate site conditions, or delays beyond Fenster Glazing & Locks Ltd’s control may be charged to the client.
A16: 10. Health and Safety Fenster Glazing & Locks Ltd shall carry out all works in accordance with applicable UK health and safety legislation. The client shall be responsible for ensuring that the site and working environment comply with all relevant health and safety requirements, including the Construction (Design and Management) Regulations 2015. Fenster Glazing & Locks Ltd reserves the right to suspend works without penalty where site conditions are deemed unsafe or non-compliant with applicable health and safety requirements.
A17: 11. Cancellation and Postponement Should the client cancel or postpone the contract following procurement of materials or commencement of works, Fenster Glazing & Locks Ltd reserves the right to retain the deposit and recover any additional costs incurred up to the date of cancellation or postponement. All goods supplied by Fenster Glazing & Locks Ltd are bespoke or made to order, and retention of the deposit reflects costs incurred in procurement, manufacture, and administration.
... A27: 20. Amendments to Terms and Conditions Fenster Glazing & Locks Ltd reserves the right to amend these Terms and Conditions from time to time. Where any material amendments are made, clients will be notified in writing. Any amendments shall apply to future contracts only and shall not affect existing agreements unless agreed in writing.
